reflex_simpleicons/__init__.py
reflex_simpleicons/simpleicons.py
reflex_simpleicons/data/brands_color.py
reflex_simpleicons/data/brands_svg.py
reflex_simpleicons-0.0.6.dist-info/METADATA
reflex_simpleicons-0.0.6.dist-info/WHEEL
reflex_simpleicons-0.0.6.dist-info/top_level.txt
reflex_simpleicons-0.0.6.dist-info/RECORD
