Metadata-Version: 2.2
Name: reflex-simpleicons
Version: 0.0.6
Summary: Reflex Custom Component for Simple Icons
Author-email: cllatser <carlos@llatser.dev>
License: Apache-2.0
Project-URL: Homepage, https://github.com/cllatser/reflex-simpleicons
Project-URL: homepage, https://github.com/cllatser/reflex-simpleicons
Project-URL: source, https://github.com/cllatser/reflex-simpleicons
Keywords: reflex,reflex-custom-components,custom-components,icons,simpleicons
Classifier: Development Status :: 4 - Beta
Requires-Python: >=3.8
Requires-Dist: reflex>=0.4.2
Provides-Extra: dev
Requires-Dist: build; extra == "dev"
Requires-Dist: twine; extra == "dev"
